cdt/__init__.py
cdt/audio_processing.py
cdt/cdt.py
cdt/data_processing.py
cdt/document_processing.py
cdt/image_processing.py
cdt/text_processing.py
cdt/video_processing.py
cdt.ai-1.0.dist-info/METADATA
cdt.ai-1.0.dist-info/WHEEL
cdt.ai-1.0.dist-info/top_level.txt
cdt.ai-1.0.dist-info/RECORD
